igbot_impl/__init__.py
igbot_impl/llm/__init__.py
igbot_impl/llm/basic_llm.py
igbot_impl/llm/one_use_llm.py
igbot_impl/llm/tool_aware_llm.py
igbot_impl/llm/tool_aware_llm_response_merger.py
igbot_impl/memory/__init__.py
igbot_impl/memory/chat_history.py
igbot_impl/memory/chat_history_view.py
igbot_impl/memory/no_memory.py
igbot_impl/memory/rolling_chat_history.py
igbot_impl/retriever/__init__.py
igbot_impl/retriever/default_retriever.py
igbot_impl/retriever/embedding_filter.py
igbot_impl/retriever/extractor.py
igbot_impl/retriever/filter.py
igbot_impl/retriever/multi_query.py
igbot_impl/retriever/self_query.py
igbot_implementation-0.0.29.dist-info/METADATA
igbot_implementation-0.0.29.dist-info/WHEEL
igbot_implementation-0.0.29.dist-info/top_level.txt
igbot_implementation-0.0.29.dist-info/RECORD
