Metadata-Version: 2.4
Name: igbot_implementation
Version: 0.0.29
Summary: Implementation of concrete classes for igbot
Author-email: Igor Kopeć <igor.kopec95@gmail.com>
License: LGPL-3.0-or-later
Requires-Python: >=3.12
Requires-Dist: igbot-base
Requires-Dist: langchain
Requires-Dist: openai
